optic/__init__.py
optic_document_django-0.1.4.dist-info/LICENSE
optic_document_django-0.1.4.dist-info/METADATA
optic_document_django-0.1.4.dist-info/WHEEL
optic_document_django-0.1.4.dist-info/top_level.txt
optic_document_django-0.1.4.dist-info/RECORD
