Metadata-Version: 2.1
Name: optic-document-django
Version: 0.1.4
Summary: Document a django API with Optic
Home-page: https://github.com/opticdev/api-ingestion
Author: Optic
Author-email: acunniffe@gmail.com
License: MIT
Platform: UNKNOWN
Requires-Dist: django
